{
  "meta": {
    "provider": "Veri Asia",
    "description": "Asian football probability engine \u2014 the gold standard for match probability in Asian leagues.",
    "model": "PV10 v7 Unified",
    "market": "DNB (Draw No Bet, AH 0.0)",
    "benchmark": "Pinnacle Starting Prices",
    "leagues": [
      "A-League",
      "J.League",
      "K-League 1",
      "Saudi Pro League",
      "Chinese Super League"
    ],
    "updated_at": "2026-04-08T21:10:33Z",
    "source": "https://github.com/veriasia/engine",
    "methodology": "Four-pillar performance rating (Finishing, Creation, Progression, Defensive) with per-league optimised pillar weights, logistic probability model, and market SP blending. Walk-forward backtest with no data leakage."
  },
  "model_accuracy": {
    "description": "Brier Skill Score (BSS) vs Pinnacle starting prices. Positive = model beats the market.",
    "overall": {
      "bss_vs_pinnacle_sp_pct": -1.5709,
      "n_matches": 1747,
      "model_brier": 0.214292,
      "market_brier": 0.210978,
      "bss_this_month_pct": -1.7617,
      "n_matches_month": 26
    },
    "by_league": {
      "a_league": {
        "league_name": "A-League",
        "bss_vs_pinnacle_sp_pct": 0.5032,
        "n_sp_matches": 348,
        "bss_this_month_pct": 6.4935,
        "n_sp_matches_month": 4,
        "bss_vs_naive_pct": 6.4805,
        "n_naive_matches": 386
      },
      "j_league": {
        "league_name": "J.League",
        "bss_vs_pinnacle_sp_pct": -0.162,
        "n_sp_matches": 700,
        "bss_this_month_pct": -1.4869,
        "n_sp_matches_month": 10,
        "bss_vs_naive_pct": 7.0189,
        "n_naive_matches": 801
      },
      "k_league": {
        "league_name": "K-League 1",
        "bss_vs_pinnacle_sp_pct": -1.6453,
        "n_sp_matches": 291,
        "bss_this_month_pct": -14.9269,
        "n_sp_matches_month": 4,
        "bss_vs_naive_pct": 2.6848,
        "n_naive_matches": 490
      },
      "saudi_pro_league": {
        "league_name": "Saudi Pro League",
        "bss_vs_pinnacle_sp_pct": -3.3904,
        "n_sp_matches": 51,
        "bss_this_month_pct": null,
        "n_sp_matches_month": 0,
        "bss_vs_naive_pct": 26.6876,
        "n_naive_matches": 702
      },
      "chinese_super_league": {
        "league_name": "Chinese Super League",
        "bss_vs_pinnacle_sp_pct": -8.3047,
        "n_sp_matches": 357,
        "bss_this_month_pct": -2.6566,
        "n_sp_matches_month": 8,
        "bss_vs_naive_pct": 32.2178,
        "n_naive_matches": 365
      }
    }
  },
  "locked_plays": {
    "description": "Timestamped value plays locked pre-match. All plays verifiable against match_repo.",
    "summary": {
      "total_plays": 41,
      "wins": 13,
      "losses": 13,
      "pushes": 15,
      "total_staked": 40.5,
      "total_pl": 0.99,
      "roi_pct": 2.44,
      "avg_odds": 2.12
    },
    "by_league": {
      "A-League": {
        "plays": 6,
        "wins": 2,
        "losses": 2,
        "pushes": 2,
        "staked": 6.0,
        "pl": -0.49,
        "roi_pct": -8.17
      },
      "J.League": {
        "plays": 19,
        "wins": 5,
        "losses": 7,
        "pushes": 7,
        "staked": 19.0,
        "pl": -3.08,
        "roi_pct": -16.21
      },
      "K-League 1": {
        "plays": 7,
        "wins": 4,
        "losses": 1,
        "pushes": 2,
        "staked": 7.0,
        "pl": 1.95,
        "roi_pct": 27.86
      },
      "Chinese Super League": {
        "plays": 5,
        "wins": 2,
        "losses": 1,
        "pushes": 2,
        "staked": 5.0,
        "pl": 4.11,
        "roi_pct": 82.2
      },
      "Saudi Pro League": {
        "plays": 4,
        "wins": 0,
        "losses": 2,
        "pushes": 2,
        "staked": 3.5,
        "pl": -1.5,
        "roi_pct": -42.86
      }
    },
    "clv": {
      "n_plays_with_closing": 41,
      "n_clv_positive": 18,
      "avg_clv_pct": 0.0
    },
    "plays": [
      {
        "date": "2026-03-17",
        "league": "A-League",
        "home": "Sydney",
        "away": "Melbourne City FC",
        "proposition": "away",
        "locked_odds": 2.3,
        "pinnacle_closing_odds": 2.3,
        "clv_pct": 0.0,
        "result": "profit",
        "pl_units": 1.3,
        "reasoning": "",
        "commitment_cleartext": "PV-a_league-19577428|A-League|2026-03-17|Sydney|Melbourne City FC|away|2.30|6.52|2026-03-17 12:23:03.650227",
        "commitment_hash": "e6b6b34fee5e50d4a3680395e833e8a2164f29a39adcf23d4d79c4a400800775"
      },
      {
        "date": "2026-03-18",
        "league": "J.League",
        "home": "Cerezo Osaka",
        "away": "Fagiano Okayama FC",
        "proposition": "home",
        "locked_odds": 1.5,
        "pinnacle_closing_odds": 1.51,
        "clv_pct": -0.66,
        "result": "loss",
        "pl_units": -1.0,
        "reasoning": "",
        "commitment_cleartext": "PV-j_league-19630392|J.League|2026-03-18|Cerezo Osaka|Fagiano Okayama FC|home|1.50|2.04|2026-03-17 12:42:37.590904",
        "commitment_hash": "fd37f6522972b1769e0d3d5d9612bc8f03d4f519fbd6050acea22ae2ed9bf0d8"
      },
      {
        "date": "2026-03-18",
        "league": "J.League",
        "home": "V-Varen Nagasaki",
        "away": "Kyoto Sanga",
        "proposition": "home",
        "locked_odds": 2.1,
        "pinnacle_closing_odds": 2.02,
        "clv_pct": 3.96,
        "result": "loss",
        "pl_units": -1.0,
        "reasoning": "",
        "commitment_cleartext": "PV-j_league-19630389|J.League|2026-03-18|V-Varen Nagasaki|Kyoto Sanga|home|2.10|3.45|2026-03-17 21:52:25.552322",
        "commitment_hash": "f5f141f11001be919a2c39715e116214145ec40fa76789cf0cbf7d96d8a05d5b"
      },
      {
        "date": "2026-03-18",
        "league": "J.League",
        "home": "Mito Hollyhock",
        "away": "Yokohama F. Marinos",
        "proposition": "home",
        "locked_odds": 1.83,
        "pinnacle_closing_odds": 1.71,
        "clv_pct": 7.02,
        "result": "profit",
        "pl_units": 0.83,
        "reasoning": "",
        "commitment_cleartext": "PV-j_league-19630398|J.League|2026-03-18|Mito Hollyhock|Yokohama F. Marinos|home|1.83|3.98|2026-03-17 21:52:25.717482",
        "commitment_hash": "f4e72168e1721bd5f59d92ba14fd3de80749579a539930a08c3bb2bf9cfb3857"
      },
      {
        "date": "2026-03-18",
        "league": "J.League",
        "home": "Urawa Red Diamonds",
        "away": "Kashiwa Reysol",
        "proposition": "home",
        "locked_odds": 2.18,
        "pinnacle_closing_odds": 2.44,
        "clv_pct": -10.66,
        "result": "push",
        "pl_units": 0.0,
        "reasoning": "",
        "commitment_cleartext": "PV-j_league-19630397|J.League|2026-03-18|Urawa Red Diamonds|Kashiwa Reysol|home|2.18|4.31|2026-03-17 12:42:38.815373",
        "commitment_hash": "69d6619e7a2fa0dcdc6e7607301cbf1b1abcea2a92af95b57f509c375919f4c3"
      },
      {
        "date": "2026-03-18",
        "league": "J.League",
        "home": "Nagoya Grampus",
        "away": "Sanfrecce Hiroshima",
        "proposition": "home",
        "locked_odds": 2.33,
        "pinnacle_closing_odds": 2.84,
        "clv_pct": -17.96,
        "result": "profit",
        "pl_units": 1.33,
        "reasoning": "",
        "commitment_cleartext": "PV-j_league-19630393|J.League|2026-03-18|Nagoya Grampus|Sanfrecce Hiroshima|home|2.33|3.10|2026-03-17 12:42:38.274894",
        "commitment_hash": "f7b783a6c05d6f40e55a08a8b05743fe78e2ee8732d9709bfbc4d150ea30afd3"
      },
      {
        "date": "2026-03-18",
        "league": "J.League",
        "home": "Vissel Kobe",
        "away": "Gamba Osaka",
        "proposition": "home",
        "locked_odds": 1.39,
        "pinnacle_closing_odds": 1.41,
        "clv_pct": -1.42,
        "result": "push",
        "pl_units": 0.0,
        "reasoning": "",
        "commitment_cleartext": "PV-j_league-19630391|J.League|2026-03-18|Vissel Kobe|Gamba Osaka|home|1.39|4.51|2026-03-17 12:42:37.896296",
        "commitment_hash": "2038fa7abfbb4750fb5e32d066f80942d98465abfc644d49b6c780d9bf9b62dd"
      },
      {
        "date": "2026-03-18",
        "league": "J.League",
        "home": "Tokyo Verdy",
        "away": "Kawasaki Frontale",
        "proposition": "home",
        "locked_odds": 2.49,
        "pinnacle_closing_odds": 2.65,
        "clv_pct": -6.04,
        "result": "loss",
        "pl_units": -1.0,
        "reasoning": "",
        "commitment_cleartext": "PV-j_league-19630395|J.League|2026-03-18|Tokyo Verdy|Kawasaki Frontale|home|2.49|5.51|2026-03-17 12:42:38.406926",
        "commitment_hash": "de9b4898fd57211cb9b1a0013bde0fdf997742ed39f509e3874404b2abed905f"
      },
      {
        "date": "2026-03-18",
        "league": "K-League 1",
        "home": "Incheon United",
        "away": "Daejeon Hana Citizen",
        "proposition": "away",
        "locked_odds": 2.15,
        "pinnacle_closing_odds": 2.12,
        "clv_pct": 1.42,
        "result": "profit",
        "pl_units": 1.15,
        "reasoning": "",
        "commitment_cleartext": "PV-k_league-19648212|K-League 1|2026-03-18|Incheon United|Daejeon Hana Citizen|away|2.15|7.50|2026-03-17 12:42:36.702886",
        "commitment_hash": "cd08627d5353d97a4c68347c0f714c9509e91b1df48f5539cc5569f874bbeab7"
      },
      {
        "date": "2026-03-18",
        "league": "K-League 1",
        "home": "Pohang Steelers",
        "away": "Seoul FC",
        "proposition": "away",
        "locked_odds": 1.77,
        "pinnacle_closing_odds": 1.75,
        "clv_pct": 1.14,
        "result": "profit",
        "pl_units": 0.77,
        "reasoning": "",
        "commitment_cleartext": "PV-k_league-19648209|K-League 1|2026-03-18|Pohang Steelers|Seoul FC|away|1.77|2.91|2026-03-17 12:42:36.867550",
        "commitment_hash": "50829918a23760694fe73bd2a6bfb1018d5b08164c11afa63c41fac2e2a7c435"
      },
      {
        "date": "2026-03-21",
        "league": "A-League",
        "home": "Melbourne Victory",
        "away": "Central Coast Mariners",
        "proposition": "home",
        "locked_odds": 1.21,
        "pinnacle_closing_odds": 1.21,
        "clv_pct": 0.0,
        "result": "profit",
        "pl_units": 0.21,
        "reasoning": "HOME lock @ 1.21 (edge +5.2% vs threshold 5.0%). Model fair: 1.15 (87.2% implied). Pinnacle AH 0.0: 1.21 (82.6% implied). Components: market=0.828(w=0.55), PV10-last2=0.702(w=0.11), PV10-last5=0.647(w=0.16), PV10-season=0.595(w=0.04), PV10-H/A=0.597(w=0.14). Adjustments: home_adv=1.020, calibration=+6.0pp.",
        "commitment_cleartext": "PV-a_league-19577493|A-League|2026-03-21|Melbourne Victory|Central Coast Mariners|home|1.21|5.22|2026-03-19 15:21:38.591106",
        "commitment_hash": "43f1ebf26d7be6bd2ff9a1f7402771c2df367db2b45e7530fc00f4e35306f327"
      },
      {
        "date": "2026-03-21",
        "league": "A-League",
        "home": "Auckland",
        "away": "Macarthur",
        "proposition": "home",
        "locked_odds": 1.31,
        "pinnacle_closing_odds": 1.33,
        "clv_pct": -1.5,
        "result": "loss",
        "pl_units": -1.0,
        "reasoning": "HOME lock @ 1.31 (edge +5.7% vs threshold 5.0%). Model fair: 1.24 (80.4% implied). Pinnacle AH 0.0: 1.31 (76.3% implied). Components: market=0.737(w=0.55), PV10-last2=0.797(w=0.11), PV10-last5=0.585(w=0.16), PV10-season=0.555(w=0.04), PV10-H/A=0.582(w=0.14). Adjustments: home_adv=1.020, calibration=+6.0pp.",
        "commitment_cleartext": "PV-a_league-19577492|A-League|2026-03-21|Auckland|Macarthur|home|1.31|5.65|2026-03-20 14:53:13.431269",
        "commitment_hash": "9630b3373e828919f55ece23d58c734fedfdb42bc80d2b7bac014b4281a96492"
      },
      {
        "date": "2026-03-21",
        "league": "Chinese Super League",
        "home": "Henan Songshan Longmen",
        "away": "Wuhan Three Towns",
        "proposition": "home",
        "locked_odds": 1.22,
        "pinnacle_closing_odds": 1.19,
        "clv_pct": 2.52,
        "result": "push",
        "pl_units": 0.0,
        "reasoning": "HOME lock @ 1.22 (edge +4.3% vs threshold 3.5%). Model fair: 1.17 (85.6% implied). Pinnacle AH 0.0: 1.22 (82.0% implied). Components: market=0.819(w=0.80), PV10-last2=0.690(w=0.03), PV10-last5=0.690(w=0.05), PV10-season=0.690(w=0.02), PV10-H/A=0.900(w=0.10). Adjustments: travel=0.950, home_adv=1.020.",
        "commitment_cleartext": "PV-chinese_super_league-19674797|Chinese Super League|2026-03-21|Henan Songshan Longmen|Wuhan Three Towns|home|1.22|4.27|2026-03-20 23:49:29.845176",
        "commitment_hash": "7222791e938cfe7be6af530579804d9a2fd8956f88738cafc040df0b1b3b824d"
      },
      {
        "date": "2026-03-21",
        "league": "Chinese Super League",
        "home": "Beijing Guoan",
        "away": "Shanghai Shenhua",
        "proposition": "away",
        "locked_odds": 2.24,
        "pinnacle_closing_odds": 2.26,
        "clv_pct": -0.88,
        "result": "push",
        "pl_units": 0.0,
        "reasoning": "AWAY lock @ 2.24 (edge +7.2% vs threshold 3.5%). Model fair: 2.09 (47.7% implied). Pinnacle AH 0.0: 2.24 (44.6% implied). Components: market=0.571(w=0.80), PV10-last2=0.311(w=0.03), PV10-last5=0.311(w=0.05), PV10-season=0.311(w=0.02), PV10-H/A=0.100(w=0.10). Adjustments: home_adv=1.020.",
        "commitment_cleartext": "PV-chinese_super_league-19674799|Chinese Super League|2026-03-21|Beijing Guoan|Shanghai Shenhua|away|2.24|7.18|2026-03-20 10:00:38.801989",
        "commitment_hash": "a0b8a5f25ae0bc09f4804941b7fe98038120ff82a9b6ef9a1c4986801a82e446"
      },
      {
        "date": "2026-03-21",
        "league": "Chinese Super League",
        "home": "Yunnan Yukun",
        "away": "Shandong Taishan",
        "proposition": "home",
        "locked_odds": 2.73,
        "pinnacle_closing_odds": 2.43,
        "clv_pct": 12.35,
        "result": "profit",
        "pl_units": 1.73,
        "reasoning": "HOME lock @ 2.73 (edge +7.1% vs threshold 3.5%). Model fair: 2.55 (39.2% implied). Pinnacle AH 0.0: 2.73 (36.6% implied). Components: market=0.350(w=0.80), PV10-last2=0.478(w=0.03), PV10-last5=0.478(w=0.05), PV10-season=0.478(w=0.02), PV10-H/A=0.900(w=0.10). Adjustments: home_adv=1.020.",
        "commitment_cleartext": "PV-chinese_super_league-19674794|Chinese Super League|2026-03-21|Yunnan Yukun|Shandong Taishan|home|2.73|7.06|2026-03-20 10:00:40.243692",
        "commitment_hash": "e173d257598003275b47f1a8e5673ae9b45d8e3cee8c855cb51c39d3a58a4b03"
      },
      {
        "date": "2026-03-21",
        "league": "Chinese Super League",
        "home": "Qingdao West Coast",
        "away": "Shenzhen Peng City",
        "proposition": "away",
        "locked_odds": 2.29,
        "pinnacle_closing_odds": 2.37,
        "clv_pct": -3.38,
        "result": "loss",
        "pl_units": -1.0,
        "reasoning": "AWAY lock @ 2.29 (edge +3.6% vs threshold 3.5%). Model fair: 2.21 (45.2% implied). Pinnacle AH 0.0: 2.29 (43.7% implied). Components: market=0.580(w=0.80), PV10-last2=0.469(w=0.03), PV10-last5=0.469(w=0.05), PV10-season=0.469(w=0.02), PV10-H/A=0.100(w=0.10). Adjustments: home_adv=1.020.",
        "commitment_cleartext": "PV-chinese_super_league-19674795|Chinese Super League|2026-03-21|Qingdao West Coast|Shenzhen Peng City|away|2.29|3.62|2026-03-21 03:06:16.061381",
        "commitment_hash": "e622f4552cc1c098a3dd0abd2cb284c5907510d88fec9eca43dad1bbf0c83e93"
      },
      {
        "date": "2026-03-21",
        "league": "J.League",
        "home": "Fagiano Okayama FC",
        "away": "V-Varen Nagasaki",
        "proposition": "home",
        "locked_odds": 1.62,
        "pinnacle_closing_odds": 1.61,
        "clv_pct": 0.62,
        "result": "loss",
        "pl_units": -1.0,
        "reasoning": "HOME lock @ 1.62 (edge +12.5% vs threshold 2.0%). Model fair: 1.44 (69.5% implied). Pinnacle AH 0.0: 1.62 (61.7% implied). Components: market=0.598(w=0.70), PV10-last2=0.501(w=0.06), PV10-last5=0.550(w=0.06), PV10-season=0.522(w=0.06), PV10-H/A=0.652(w=0.12). Adjustments: travel=0.950, home_adv=1.092, calibration=+6.0pp.",
        "commitment_cleartext": "PV-j_league-19630381|J.League|2026-03-21|Fagiano Okayama FC|V-Varen Nagasaki|home|1.62|12.50|2026-03-20 10:27:29.422701",
        "commitment_hash": "fc06a66a9636b1991402b60054a1c67b3cf44af0cebe4bf5bb7e49d9b0a62a05"
      },
      {
        "date": "2026-03-21",
        "league": "J.League",
        "home": "Avispa Fukuoka",
        "away": "Gamba Osaka",
        "proposition": "home",
        "locked_odds": 2.38,
        "pinnacle_closing_odds": 2.79,
        "clv_pct": -14.7,
        "result": "push",
        "pl_units": 0.0,
        "reasoning": "HOME lock @ 2.38 (edge +9.2% vs threshold 2.0%). Model fair: 2.18 (45.8% implied). Pinnacle AH 0.0: 2.38 (42.0% implied). Components: market=0.402(w=0.70), PV10-last2=0.476(w=0.06), PV10-last5=0.383(w=0.06), PV10-season=0.356(w=0.06), PV10-H/A=0.397(w=0.12). Adjustments: home_adv=1.051, calibration=+5.7pp.",
        "commitment_cleartext": "PV-j_league-19630380|J.League|2026-03-21|Avispa Fukuoka|Gamba Osaka|home|2.38|9.17|2026-03-19 15:21:43.141499",
        "commitment_hash": "b56381122edc2283dba067325d8b52eb75c6fd5a57c86b5ae1a15da752037e4f"
      },
      {
        "date": "2026-03-21",
        "league": "K-League 1",
        "home": "Daejeon Hana Citizen",
        "away": "Jeonbuk Motors",
        "proposition": "away",
        "locked_odds": 1.81,
        "pinnacle_closing_odds": 1.99,
        "clv_pct": -9.05,
        "result": "profit",
        "pl_units": 0.81,
        "reasoning": "AWAY lock @ 1.81 (edge +9.7% vs threshold 2.5%). Model fair: 1.65 (60.8% implied). Pinnacle AH 0.0: 1.81 (55.2% implied). Components: market=0.464(w=0.80), PV10-last2=0.100(w=0.08), PV10-last5=0.100(w=0.04), PV10-season=0.100(w=0.02), PV10-H/A=0.100(w=0.06). Adjustments: home_adv=1.033.",
        "commitment_cleartext": "PV-k_league-19648208|K-League 1|2026-03-21|Daejeon Hana Citizen|Jeonbuk Motors|away|1.81|9.70|2026-03-20 10:15:06.180159",
        "commitment_hash": "87667a0c9a753a3726b7321f53fe68d8998704bbe8cbe53f80d8e1630bd938b9"
      },
      {
        "date": "2026-03-22",
        "league": "A-League",
        "home": "Sydney",
        "away": "Newcastle United Jets",
        "proposition": "home",
        "locked_odds": 1.71,
        "pinnacle_closing_odds": 1.62,
        "clv_pct": 5.56,
        "result": "loss",
        "pl_units": -1.0,
        "reasoning": "HOME lock @ 1.71 (edge +6.2% vs threshold 5.0%). Model fair: 1.61 (62.0% implied). Pinnacle AH 0.0: 1.71 (58.5% implied). Components: market=0.566(w=0.55), PV10-last2=0.597(w=0.11), PV10-last5=0.547(w=0.16), PV10-season=0.492(w=0.04), PV10-H/A=0.518(w=0.14). Adjustments: home_adv=1.031, calibration=+3.5pp.",
        "commitment_cleartext": "PV-a_league-19577494|A-League|2026-03-22|Sydney|Newcastle United Jets|home|1.71|6.21|2026-03-21 07:50:15.821548",
        "commitment_hash": "6f0e96cc8f0be449db3d00f9a88bfa4f8033dcca2c42c3b28bc9256493292e20"
      },
      {
        "date": "2026-03-22",
        "league": "J.League",
        "home": "Tokyo Verdy",
        "away": "FC Tokyo",
        "proposition": "home",
        "locked_odds": 2.85,
        "pinnacle_closing_odds": 3.21,
        "clv_pct": -11.21,
        "result": "push",
        "pl_units": 0.0,
        "reasoning": "HOME lock @ 2.85 (edge +7.5% vs threshold 2.0%). Model fair: 2.65 (37.7% implied). Pinnacle AH 0.0: 2.85 (35.1% implied). Components: market=0.336(w=0.70), PV10-last2=0.454(w=0.06), PV10-last5=0.368(w=0.06), PV10-season=0.341(w=0.06), PV10-H/A=0.402(w=0.12). Adjustments: home_adv=1.082, calibration=+3.4pp.",
        "commitment_cleartext": "PV-j_league-19630385|J.League|2026-03-22|Tokyo Verdy|FC Tokyo|home|2.85|7.55|2026-03-20 10:27:30.020651",
        "commitment_hash": "503345ccbbb3898ef3e2246dcfa045255e899803f61091b1d7cc73b78f2e07bb"
      },
      {
        "date": "2026-03-22",
        "league": "J.League",
        "home": "Kashima Antlers",
        "away": "JEF United",
        "proposition": "home",
        "locked_odds": 1.24,
        "pinnacle_closing_odds": 1.2,
        "clv_pct": 3.33,
        "result": "profit",
        "pl_units": 0.24,
        "reasoning": "HOME lock @ 1.24 (edge +5.1% vs threshold 2.0%). Model fair: 1.18 (84.4% implied). Pinnacle AH 0.0: 1.24 (80.6% implied). Components: market=0.768(w=0.70), PV10-last2=0.610(w=0.06), PV10-last5=0.551(w=0.06), PV10-season=0.486(w=0.06), PV10-H/A=0.559(w=0.12). Adjustments: home_adv=1.025, calibration=+6.0pp.",
        "commitment_cleartext": "PV-j_league-19630388|J.League|2026-03-22|Kashima Antlers|JEF United|home|1.24|5.08|2026-03-20 10:27:30.622649",
        "commitment_hash": "eb70a6ad36bd20ccd62fc17da7e25482b734f9a5cd2b388be3aa4aaeeacf2546"
      },
      {
        "date": "2026-03-22",
        "league": "J.League",
        "home": "Kyoto Sanga",
        "away": "Nagoya Grampus",
        "proposition": "home",
        "locked_odds": 1.69,
        "pinnacle_closing_odds": 1.81,
        "clv_pct": -6.63,
        "result": "push",
        "pl_units": 0.0,
        "reasoning": "HOME lock @ 1.69 (edge +5.0% vs threshold 2.0%). Model fair: 1.61 (62.2% implied). Pinnacle AH 0.0: 1.69 (59.2% implied). Components: market=0.562(w=0.70), PV10-last2=0.429(w=0.06), PV10-last5=0.458(w=0.06), PV10-season=0.438(w=0.06), PV10-H/A=0.524(w=0.12). Adjustments: travel=0.950, home_adv=1.072, calibration=+6.0pp.",
        "commitment_cleartext": "PV-j_league-19630383|J.League|2026-03-22|Kyoto Sanga|Nagoya Grampus|home|1.69|4.97|2026-03-19 15:21:43.763922",
        "commitment_hash": "11554d921db2ad53455aedb70e00c7092d2b886a3b717651aa1dcb6005d669c7"
      },
      {
        "date": "2026-03-22",
        "league": "J.League",
        "home": "Cerezo Osaka",
        "away": "Vissel Kobe",
        "proposition": "home",
        "locked_odds": 2.35,
        "pinnacle_closing_odds": 2.03,
        "clv_pct": 15.76,
        "result": "push",
        "pl_units": 0.0,
        "reasoning": "HOME lock @ 2.35 (edge +5.4% vs threshold 2.0%). Model fair: 2.23 (44.9% implied). Pinnacle AH 0.0: 2.35 (42.6% implied). Components: market=0.408(w=0.70), PV10-last2=0.379(w=0.06), PV10-last5=0.393(w=0.06), PV10-season=0.392(w=0.06), PV10-H/A=0.401(w=0.12). Adjustments: home_adv=1.025, calibration=+5.5pp.",
        "commitment_cleartext": "PV-j_league-19630382|J.League|2026-03-22|Cerezo Osaka|Vissel Kobe|home|2.35|5.38|2026-03-19 15:21:43.971480",
        "commitment_hash": "30b5fd36fb045e0fff40c83c19b0299e48508b9445719af54bbfeb2e423af6ce"
      },
      {
        "date": "2026-03-22",
        "league": "J.League",
        "home": "Urawa Red Diamonds",
        "away": "Machida Zelvia",
        "proposition": "home",
        "locked_odds": 1.96,
        "pinnacle_closing_odds": 2.0,
        "clv_pct": -2.0,
        "result": "loss",
        "pl_units": -1.0,
        "reasoning": "HOME lock @ 1.96 (edge +13.3% vs threshold 2.0%). Model fair: 1.73 (57.8% implied). Pinnacle AH 0.0: 1.96 (51.0% implied). Components: market=0.491(w=0.70), PV10-last2=0.595(w=0.06), PV10-last5=0.531(w=0.06), PV10-season=0.571(w=0.06), PV10-H/A=0.528(w=0.12). Adjustments: home_adv=1.025, calibration=+6.0pp.",
        "commitment_cleartext": "PV-j_league-19630387|J.League|2026-03-22|Urawa Red Diamonds|Machida Zelvia|home|1.96|13.29|2026-03-19 15:21:44.593846",
        "commitment_hash": "59fca533fc96ad28cb7f76ee2b6976d3855eb078f3ae63a6b628018861f7537c"
      },
      {
        "date": "2026-03-22",
        "league": "J.League",
        "home": "Kawasaki Frontale",
        "away": "Yokohama F. Marinos",
        "proposition": "home",
        "locked_odds": 1.55,
        "pinnacle_closing_odds": 1.67,
        "clv_pct": -7.19,
        "result": "loss",
        "pl_units": -1.0,
        "reasoning": "HOME lock @ 1.55 (edge +9.2% vs threshold 2.0%). Model fair: 1.42 (70.3% implied). Pinnacle AH 0.0: 1.55 (64.5% implied). Components: market=0.618(w=0.70), PV10-last2=0.488(w=0.06), PV10-last5=0.531(w=0.06), PV10-season=0.528(w=0.06), PV10-H/A=0.629(w=0.12). Adjustments: home_adv=1.025, calibration=+6.0pp.",
        "commitment_cleartext": "PV-j_league-19630379|J.League|2026-03-22|Kawasaki Frontale|Yokohama F. Marinos|home|1.55|9.15|2026-03-20 10:27:30.820652",
        "commitment_hash": "9fa46669937ea238f808d8f865901f4caa95710dbae1b1a9b2bd9309e90ac3d0"
      },
      {
        "date": "2026-03-22",
        "league": "K-League 1",
        "home": "Ulsan Hyundai",
        "away": "Gimcheon Sangmu",
        "proposition": "home",
        "locked_odds": 1.56,
        "pinnacle_closing_odds": 1.55,
        "clv_pct": 0.65,
        "result": "push",
        "pl_units": 0.0,
        "reasoning": "HOME lock @ 1.56 (edge +2.6% vs threshold 2.5%). Model fair: 1.52 (65.8% implied). Pinnacle AH 0.0: 1.56 (64.1% implied). Components: market=0.620(w=0.80), PV10-last2=0.591(w=0.08), PV10-last5=0.535(w=0.04), PV10-season=0.535(w=0.02), PV10-H/A=0.624(w=0.06). Adjustments: home_adv=1.025.",
        "commitment_cleartext": "PV-k_league-19648206|K-League 1|2026-03-22|Ulsan Hyundai|Gimcheon Sangmu|home|1.56|2.63|2026-03-21 11:42:52.354362",
        "commitment_hash": "6215932bdf98c76d2ff7a3a4f92b034a3592f6e1f3723f605a38ef11caed0de8"
      },
      {
        "date": "2026-03-22",
        "league": "K-League 1",
        "home": "Seoul FC",
        "away": "Gwangju",
        "proposition": "home",
        "locked_odds": 1.22,
        "pinnacle_closing_odds": 1.22,
        "clv_pct": 0.0,
        "result": "profit",
        "pl_units": 0.22,
        "reasoning": "HOME lock @ 1.22 (edge +2.5% vs threshold 2.5%). Model fair: 1.19 (83.9% implied). Pinnacle AH 0.0: 1.22 (82.0% implied). Components: market=0.783(w=0.80), PV10-last2=0.900(w=0.08), PV10-last5=0.786(w=0.04), PV10-season=0.786(w=0.02), PV10-H/A=0.100(w=0.06). Adjustments: home_adv=1.025.",
        "commitment_cleartext": "PV-k_league-19648207|K-League 1|2026-03-22|Seoul FC|Gwangju|home|1.22|2.52|2026-03-21 03:06:09.020688",
        "commitment_hash": "33ce626a4c879373cffad0b1557db71361ae2030a866b6820a543947b07dc6c5"
      },
      {
        "date": "2026-03-27",
        "league": "J.League",
        "home": "Vissel Kobe",
        "away": "Sanfrecce Hiroshima",
        "proposition": "home",
        "locked_odds": 1.91,
        "pinnacle_closing_odds": 2.04,
        "clv_pct": -6.37,
        "result": "profit",
        "pl_units": 0.91,
        "reasoning": "HOME lock @ 1.91 (soft-lock edge +7.9%). Confirmed (early): CLV +3.2% at T-1385min. Current pin: 1.85, fair: 1.70.",
        "commitment_cleartext": "PV-j_league-19630369|J.League|2026-03-27|Vissel Kobe|Sanfrecce Hiroshima|home|1.91|7.91|2026-03-26 10:54:54.274241",
        "commitment_hash": "e49759f08292e6bac24cec3f91626ee76cdaced7bc7ee657865354faf0c16dc7"
      },
      {
        "date": "2026-03-28",
        "league": "J.League",
        "home": "Machida Zelvia",
        "away": "Kawasaki Frontale",
        "proposition": "home",
        "locked_odds": 1.49,
        "pinnacle_closing_odds": 1.32,
        "clv_pct": 12.88,
        "result": "push",
        "pl_units": 0.0,
        "reasoning": "HOME lock @ 1.49 (soft-lock edge +3.5%). Confirmed (standard): CLV +12.9% at T-41min. Current pin: 1.32, fair: 1.27.",
        "commitment_cleartext": "PV-j_league-19630374|J.League|2026-03-28|Machida Zelvia|Kawasaki Frontale|home|1.49|3.47|2026-03-28 04:18:09.893983",
        "commitment_hash": "c85de5dd1a4e7ad2e6b38bd47ebaeb2cb807c791554c5f8ee615aa69cd3d9b79"
      },
      {
        "date": "2026-03-28",
        "league": "K-League 1",
        "home": "Pohang Steelers",
        "away": "Gangwon FC",
        "proposition": "away",
        "locked_odds": 1.91,
        "pinnacle_closing_odds": 1.66,
        "clv_pct": 15.06,
        "result": "loss",
        "pl_units": -1.0,
        "reasoning": "AWAY lock @ 1.91 (soft-lock edge +3.2%). Confirmed (early): CLV +6.1% at T-5516min. Current pin: 1.80, fair: 1.67.",
        "commitment_cleartext": "PV-k_league-19648226|K-League 1|2026-03-28|Pohang Steelers|Gangwon FC|away|1.91|3.24|2026-03-24 10:03:16.133475",
        "commitment_hash": "1a447e5b45e33b87cfb6a6c9481a9e8a5529a9571ef808fc45d97c1fd69f55b7"
      },
      {
        "date": "2026-04-02",
        "league": "A-League",
        "home": "Brisbane Roar",
        "away": "Sydney",
        "proposition": "away",
        "locked_odds": 1.65,
        "pinnacle_closing_odds": 1.68,
        "clv_pct": -1.79,
        "result": "push",
        "pl_units": 0.0,
        "reasoning": "AWAY lock @ 1.65 (soft-lock edge +8.6%). Confirmed (standard): CLV -1.8% at T-49min. Current pin: 1.68, fair: 1.53.",
        "commitment_cleartext": "PV-a_league-19578597|A-League|2026-04-02|Brisbane Roar|Sydney|away|1.65|8.55|2026-04-02 09:10:54.007795",
        "commitment_hash": "29c7a36927de5ca6e701c4af44c61abc9b5f04c56a214981f0c60ef4a7d563a0"
      },
      {
        "date": "2026-04-04",
        "league": "A-League",
        "home": "Central Coast Mariners",
        "away": "Perth Glory",
        "proposition": "away",
        "locked_odds": 2.13,
        "pinnacle_closing_odds": 1.93,
        "clv_pct": 10.36,
        "result": "push",
        "pl_units": 0.0,
        "reasoning": "AWAY lock @ 2.13 (soft-lock edge +10.9%). Confirmed (early): CLV +4.4% at T-2522min. Current pin: 2.04, fair: 1.81.",
        "commitment_cleartext": "PV-a_league-19577498|A-League|2026-04-04|Central Coast Mariners|Perth Glory|away|2.13|10.94|2026-04-02 11:57:09.036977",
        "commitment_hash": "1d2080cf2d59040c111bf5c1d9e3aa6488e3f5897ad6ece1c7dde7a79c06737e"
      },
      {
        "date": "2026-04-04",
        "league": "Chinese Super League",
        "home": "Shandong Taishan",
        "away": "Dalian Yingbo",
        "proposition": "away",
        "locked_odds": 4.38,
        "pinnacle_closing_odds": 3.2,
        "clv_pct": 36.87,
        "result": "profit",
        "pl_units": 3.38,
        "reasoning": "AWAY lock @ 4.38 (soft-lock edge +12.9%). Confirmed (early): CLV +11.2% at T-265min. Current pin: 3.94, fair: 2.93.",
        "commitment_cleartext": "PV-chinese_super_league-19674790|Chinese Super League|2026-04-04|Shandong Taishan|Dalian Yingbo|away|4.38|12.89|2026-04-04 06:34:37.640284",
        "commitment_hash": "b6393e3d82e2cc3f7fd1ed3049ee51a304ad3593b74562c09b91727ebbfceca8"
      },
      {
        "date": "2026-04-04",
        "league": "J.League",
        "home": "Nagoya Grampus",
        "away": "Cerezo Osaka",
        "proposition": "home",
        "locked_odds": 1.61,
        "pinnacle_closing_odds": 1.88,
        "clv_pct": -14.36,
        "result": "profit",
        "pl_units": 0.61,
        "reasoning": "HOME lock @ 1.61 (soft-lock edge +10.3%). Confirmed (early): CLV +2.5% at T-727min. Current pin: 1.57, fair: 1.43.",
        "commitment_cleartext": "PV-j_league-19630363|J.League|2026-04-04|Nagoya Grampus|Cerezo Osaka|home|1.61|10.27|2026-04-03 17:52:22.046923",
        "commitment_hash": "1173cebda851bb3b06bde6819e2e2e52dbfdc0265228a404336b2ec09ff2e038"
      },
      {
        "date": "2026-04-05",
        "league": "J.League",
        "home": "V-Varen Nagasaki",
        "away": "Shimizu S-Pulse",
        "proposition": "home",
        "locked_odds": 1.99,
        "pinnacle_closing_odds": 2.0,
        "clv_pct": -0.5,
        "result": "loss",
        "pl_units": -1.0,
        "reasoning": "HOME lock @ 1.99 (soft-lock edge +11.8%). Confirmed (standard): CLV -0.5% at T-164min. Current pin: 2.00, fair: 1.71.",
        "commitment_cleartext": "PV-j_league-19630359|J.League|2026-04-05|V-Varen Nagasaki|Shimizu S-Pulse|home|1.99|11.80|2026-04-05 01:15:21.934522",
        "commitment_hash": "84884265a10c373000841c9ac2bc79cd65bc1ac7b4e219e0e263a31f8a68b6bb"
      },
      {
        "date": "2026-04-05",
        "league": "K-League 1",
        "home": "Anyang",
        "away": "Seoul FC",
        "proposition": "away",
        "locked_odds": 1.5,
        "pinnacle_closing_odds": 1.47,
        "clv_pct": 2.04,
        "result": "push",
        "pl_units": 0.0,
        "reasoning": "AWAY lock @ 1.50 (soft-lock edge +6.4%). Confirmed (standard): CLV +2.0% at T-48min. Current pin: 1.47, fair: 1.32.",
        "commitment_cleartext": "PV-k_league-19648198|K-League 1|2026-04-05|Anyang|Seoul FC|away|1.50|6.38|2026-04-05 04:11:18.495673",
        "commitment_hash": "1fa7db4ede704e777542ae3bf8931f6a96e9603d9dd7712e320cd5a3191a3421"
      },
      {
        "date": "2026-04-05",
        "league": "Saudi Pro League",
        "home": "Al Ettifaq",
        "away": "Al-Qadsiah",
        "proposition": "away",
        "locked_odds": 1.21,
        "pinnacle_closing_odds": 1.2,
        "clv_pct": 0.83,
        "result": "loss",
        "pl_units": -1.0,
        "reasoning": "AWAY lock @ 1.21 (soft-lock edge +9.0%). Confirmed (standard): CLV +0.8% at T-149min. Current pin: 1.20, fair: 1.11.",
        "commitment_cleartext": "PV-saudi_pro_league-19541966|Saudi Pro League|2026-04-05|Al Ettifaq|Al-Qadsiah|away|1.21|9.01|2026-04-05 15:30:18.355057",
        "commitment_hash": "3fc3bdcb8fb4412c6a1c8029a89cc08cbf6920ccc716a57bd9637d784b101cb4"
      },
      {
        "date": "2026-04-05",
        "league": "Saudi Pro League",
        "home": "Al Riyadh",
        "away": "Al Shabab",
        "proposition": "away",
        "locked_odds": 1.42,
        "pinnacle_closing_odds": 1.42,
        "clv_pct": 0.0,
        "result": "push",
        "pl_units": 0.0,
        "reasoning": "AWAY lock @ 1.42 (soft-lock edge +11.8%). Confirmed (standard): CLV +0.0% at T-149min. Current pin: 1.42, fair: 1.24.",
        "commitment_cleartext": "PV-saudi_pro_league-19541971|Saudi Pro League|2026-04-05|Al Riyadh|Al Shabab|away|1.42|11.81|2026-04-05 15:30:18.559654",
        "commitment_hash": "b7676f3e7f60beea667f82ff01738a5d0dd4c8553265b9f8a33f3c4e6fd83562"
      },
      {
        "date": "2026-04-08",
        "league": "Saudi Pro League",
        "home": "Al-Fayha",
        "away": "Al Ahli",
        "proposition": "away",
        "locked_odds": 1.25,
        "pinnacle_closing_odds": 1.19,
        "clv_pct": 5.04,
        "result": "push",
        "pl_units": 0.0,
        "reasoning": "Manual lock: value found at 1.25 before price moved in",
        "commitment_cleartext": "PV-saudi_pro_league-19541987|Saudi Pro League|2026-04-08|Al-Fayha|Al Ahli|away|1.25|6.31|2026-04-07 09:27:41.763449",
        "commitment_hash": "9e5d30355a83aa140306749bac2980acea2086685f7f1158e5313ed475c08f4f"
      },
      {
        "date": "2026-04-08",
        "league": "Saudi Pro League",
        "home": "Al Hilal",
        "away": "Al Kholood",
        "proposition": "away",
        "locked_odds": 11.31,
        "pinnacle_closing_odds": 14.32,
        "clv_pct": -21.02,
        "result": "loss",
        "pl_units": -0.5,
        "reasoning": "AWAY lock @ 11.31 (edge +13.1% vs threshold 7.0%). Model fair: 10.00 (10.0% implied). Pinnacle AH 0.0: 11.31 (8.8% implied). Components: market=0.900(w=0.35), Veri10-last3=0.900(w=0.07), Veri10-season=0.898(w=0.46), Veri10-H/A=0.856(w=0.13). [direct-lock: model-strong league]",
        "commitment_cleartext": "PV-saudi_pro_league-19541983|Saudi Pro League|2026-04-08|Al Hilal|Al Kholood|away|11.31|13.10|2026-04-08 06:34:55.374681",
        "commitment_hash": "9b882bd528a894aa6d44d000d52a7438375f1f1fd784196b2047a8b36f1ccc95"
      }
    ]
  }
}